mcp_coaia_sequential_thinking/__init__.py
mcp_coaia_sequential_thinking/agent_coordination.py
mcp_coaia_sequential_thinking/analysis.py
mcp_coaia_sequential_thinking/co_lint_integration.py
mcp_coaia_sequential_thinking/consensus_decision_engine.py
mcp_coaia_sequential_thinking/constitutional_core.py
mcp_coaia_sequential_thinking/creative_orientation_engine.py
mcp_coaia_sequential_thinking/creative_orientation_foundation.py
mcp_coaia_sequential_thinking/data_persistence.py
mcp_coaia_sequential_thinking/enhanced_polycentric_lattice.py
mcp_coaia_sequential_thinking/generative_agent_lattice.py
mcp_coaia_sequential_thinking/inquiry_engine.py
mcp_coaia_sequential_thinking/integration_bridge.py
mcp_coaia_sequential_thinking/logging_conf.py
mcp_coaia_sequential_thinking/models.py
mcp_coaia_sequential_thinking/polycentric_lattice.py
mcp_coaia_sequential_thinking/prompts.py
mcp_coaia_sequential_thinking/resilient_connection.py
mcp_coaia_sequential_thinking/resources.py
mcp_coaia_sequential_thinking/server.py
mcp_coaia_sequential_thinking/storage.py
mcp_coaia_sequential_thinking/storage_utils.py
mcp_coaia_sequential_thinking/tension_visualization.py
mcp_coaia_sequential_thinking/testing.py
mcp_coaia_sequential_thinking/utils.py
mcp_coaia_sequential_thinking/wrapper.py
mcp_coaia_sequential_thinking-0.3.13.dist-info/METADATA
mcp_coaia_sequential_thinking-0.3.13.dist-info/WHEEL
mcp_coaia_sequential_thinking-0.3.13.dist-info/entry_points.txt
mcp_coaia_sequential_thinking-0.3.13.dist-info/licenses/LICENSE
mcp_coaia_sequential_thinking-0.3.13.dist-info/RECORD
