Metadata-Version: 2.4
Name: mcp-coaia-sequential-thinking
Version: 0.3.13
Summary: CoAiA's Structural Core: Guiding Intelligent Agents with Foundational Creative Thinking
Project-URL: Source, https://github.com/miadisabelle/mcp-coaia-sequential-thinking
Author-email: Arben Ademi <arben.ademi@tuta.io>
License: MIT
License-File: LICENSE
Keywords: ai,coaia,creative-orientation,mcp,polycentric-lattice,sequential-thinking,structural-thinking
Requires-Python: >=3.10
Requires-Dist: mcp[cli]>=1.2.0
Requires-Dist: numpy
Requires-Dist: portalocker
Requires-Dist: pyyaml>=6.0
Requires-Dist: rich>=13.7.0
Provides-Extra: all
Requires-Dist: sequential-thinking[dev,vis,web]; extra == 'all'
Provides-Extra: dev
Requires-Dist: black>=23.0.0; extra == 'dev'
Requires-Dist: isort>=5.0.0; extra == 'dev'
Requires-Dist: mypy>=1.0.0; extra == 'dev'
Requires-Dist: pytest-cov>=4.0.0; extra == 'dev'
Requires-Dist: pytest>=7.0.0; extra == 'dev'
Provides-Extra: vis
Requires-Dist: matplotlib>=3.5.0; extra == 'vis'
Requires-Dist: numpy>=1.20.0; extra == 'vis'
Provides-Extra: web
Requires-Dist: fastapi>=0.100.0; extra == 'web'
Requires-Dist: pydantic>=2.0.0; extra == 'web'
Requires-Dist: uvicorn>=0.20.0; extra == 'web'
